[
  {
    "_id": "660091d558ca791ae9f87c2f",
    "index": 0,
    "guid": "5d14fb42-43ac-4bb2-994a-3995c5a28ce0",
    "isActive": true,
    "balance": "$1,899.85",
    "picture": "http://placehold.it/32x32",
    "age": 37,
    "eyeColor": "blue",
    "name": "Rosa Callahan",
    "gender": "male",
    "company": "ZIDOX",
    "email": "rosacallahan@zidox.com",
    "phone": "+1 (953) 554-2569",
    "address": "248 Remsen Street, Cataract, Montana, 6730",
    "about": "Sint adipisicing elit sit ea veniam minim nostrud veniam quis. Aute ipsum quis occaecat nulla esse tempor aliqua occaecat. Ipsum sint elit occaecat laborum id minim anim irure ullamco sint deserunt enim. Fugiat occaecat quis ad eiusmod quis adipisicing dolore deserunt tempor.\r\n",
    "registered": "2015-10-02T04:47:31 +04:00",
    "latitude": 70.410608,
    "longitude": -139.650273,
    "tags": [
      "ipsum",
      "aute",
      "in",
      "in",
      "aute",
      "dolore",
      "mollit"
    ],
    "friends": [
      {
        "id": 0,
        "name": "Griffin Gilliam"
      },
      {
        "id": 1,
        "name": "House Dorsey"
      },
      {
        "id": 2,
        "name": "Moon Lawrence"
      }
    ],
    "greeting": "Hello, Rosa Callahan! You have 4 unread messages.",
    "favoriteFruit": "banana"
  },
  {
    "_id": "660091d5ba2ddba682acc3a0",
    "index": 1,
    "guid": "bd0a8904-b58b-4fe2-a829-050c14207692",
    "isActive": true,
    "balance": "$1,793.52",
    "picture": "http://placehold.it/32x32",
    "age": 37,
    "eyeColor": "blue",
    "name": "Lindsey Rutledge",
    "gender": "male",
    "company": "MAGNEATO",
    "email": "lindseyrutledge@magneato.com",
    "phone": "+1 (917) 446-3280",
    "address": "893 John Street, Grimsley, Utah, 165",
    "about": "Aliquip ex deserunt eiusmod consectetur sit ut do. Eu quis pariatur officia sint est ut id irure irure aliquip labore sint dolore incididunt. Elit ut cillum nulla esse ullamco sunt incididunt aute laborum aliquip ut. Magna voluptate ut ut et tempor cupidatat aliqua aliquip. Elit laboris duis dolor laborum est quis consectetur velit deserunt irure aliqua. Officia exercitation non eiusmod aute sit tempor eiusmod sit enim ullamco commodo veniam. Irure aliquip ipsum qui exercitation duis adipisicing sit ea laborum nulla et proident.\r\n",
    "registered": "2023-11-17T10:54:14 +05:00",
    "latitude": 60.019468,
    "longitude": 38.873865,
    "tags": [
      "minim",
      "officia",
      "ipsum",
      "sit",
      "adipisicing",
      "incididunt",
      "sunt"
    ],
    "friends": [
      {
        "id": 0,
        "name": "Nguyen Waters"
      },
      {
        "id": 1,
        "name": "Shannon Wynn"
      },
      {
        "id": 2,
        "name": "Alexis George"
      }
    ],
    "greeting": "Hello, Lindsey Rutledge! You have 8 unread messages.",
    "favoriteFruit": "banana"
  },
  {
    "_id": "660091d5a9665cf604f573e5",
    "index": 2,
    "guid": "5c4ef356-eecc-4e46-9f92-634791994cca",
    "isActive": false,
    "balance": "$1,543.00",
    "picture": "http://placehold.it/32x32",
    "age": 20,
    "eyeColor": "brown",
    "name": "Irene Mcgowan",
    "gender": "female",
    "company": "REPETWIRE",
    "email": "irenemcgowan@repetwire.com",
    "phone": "+1 (833) 563-3015",
    "address": "256 Campus Road, Foxworth, South Carolina, 3818",
    "about": "Lorem pariatur exercitation voluptate excepteur veniam ex et duis cupidatat incididunt sit reprehenderit labore. Eu cupidatat nostrud incididunt anim amet proident aliquip eiusmod tempor nostrud. Dolor duis est ea ut cupidatat. Adipisicing laboris dolor Lorem tempor veniam sit elit mollit sunt officia Lorem nostrud excepteur. Eiusmod est labore enim et fugiat adipisicing voluptate aliquip reprehenderit consectetur velit nisi do. Sint ut anim velit tempor ad occaecat esse et labore ullamco dolor eiusmod amet eiusmod.\r\n",
    "registered": "2021-12-15T05:53:26 +05:00",
    "latitude": -71.590938,
    "longitude": 8.994685,
    "tags": [
      "exercitation",
      "pariatur",
      "laborum",
      "occaecat",
      "ut",
      "id",
      "officia"
    ],
    "friends": [
      {
        "id": 0,
        "name": "Ivy Brown"
      },
      {
        "id": 1,
        "name": "Roman Sharp"
      },
      {
        "id": 2,
        "name": "Bean Walters"
      }
    ],
    "greeting": "Hello, Irene Mcgowan! You have 7 unread messages.",
    "favoriteFruit": "banana"
  },
  {
    "_id": "660091d52634f8e545b44e03",
    "index": 3,
    "guid": "0482755c-465d-436b-a38b-36cd4baa4909",
    "isActive": true,
    "balance": "$2,947.55",
    "picture": "http://placehold.it/32x32",
    "age": 21,
    "eyeColor": "blue",
    "name": "Witt Estrada",
    "gender": "male",
    "company": "EXOTERIC",
    "email": "wittestrada@exoteric.com",
    "phone": "+1 (986) 475-3288",
    "address": "932 Sackman Street, Bluffview, Wisconsin, 530",
    "about": "Irure nisi ex commodo veniam non fugiat culpa. Cillum ex ex voluptate laborum ipsum et aute. Amet sint ex officia irure culpa nulla.\r\n",
    "registered": "2023-01-12T11:28:46 +05:00",
    "latitude": -56.023228,
    "longitude": 106.309209,
    "tags": [
      "exercitation",
      "voluptate",
      "dolor",
      "est",
      "dolor",
      "commodo",
      "mollit"
    ],
    "friends": [
      {
        "id": 0,
        "name": "Janna Brady"
      },
      {
        "id": 1,
        "name": "Cora Carter"
      },
      {
        "id": 2,
        "name": "Colette Bradshaw"
      }
    ],
    "greeting": "Hello, Witt Estrada! You have 8 unread messages.",
    "favoriteFruit": "strawberry"
  },
  {
    "_id": "660091d5994cf92ecdd59b02",
    "index": 4,
    "guid": "c65c08b8-9f72-4121-86cc-2361c0375d0a",
    "isActive": false,
    "balance": "$1,526.33",
    "picture": "http://placehold.it/32x32",
    "age": 39,
    "eyeColor": "brown",
    "name": "Mann Cain",
    "gender": "male",
    "company": "PETICULAR",
    "email": "manncain@peticular.com",
    "phone": "+1 (916) 423-3253",
    "address": "847 Williamsburg Street, Santel, New Hampshire, 6709",
    "about": "Nulla minim labore irure occaecat ullamco mollit incididunt exercitation officia elit. Ea exercitation esse cupidatat laborum. Culpa amet ad minim velit enim in ullamco ullamco.\r\n",
    "registered": "2018-01-24T12:28:17 +05:00",
    "latitude": -70.965424,
    "longitude": -165.569268,
    "tags": [
      "occaecat",
      "commodo",
      "proident",
      "cillum",
      "cupidatat",
      "fugiat",
      "ipsum"
    ],
    "friends": [
      {
        "id": 0,
        "name": "Terrie Hoover"
      },
      {
        "id": 1,
        "name": "Burgess Wallace"
      },
      {
        "id": 2,
        "name": "Stafford Howell"
      }
    ],
    "greeting": "Hello, Mann Cain! You have 8 unread messages.",
    "favoriteFruit": "strawberry"
  },
  {
    "_id": "660091d52b0333929ca7199a",
    "index": 5,
    "guid": "e5400d61-e013-4406-9a45-bbb7d25e1f12",
    "isActive": true,
    "balance": "$3,704.57",
    "picture": "http://placehold.it/32x32",
    "age": 24,
    "eyeColor": "brown",
    "name": "Marissa Olson",
    "gender": "female",
    "company": "AFFLUEX",
    "email": "marissaolson@affluex.com",
    "phone": "+1 (938) 474-3716",
    "address": "253 Ocean Parkway, Kanauga, North Carolina, 3149",
    "about": "Voluptate nulla fugiat excepteur aliquip nulla culpa enim et aliqua cillum nulla. Ipsum nisi consequat eiusmod dolor elit adipisicing do id aliqua velit ea. Aliqua incididunt dolore mollit dolor ut elit est mollit veniam anim reprehenderit.\r\n",
    "registered": "2020-08-24T12:15:43 +04:00",
    "latitude": -37.836846,
    "longitude": -30.332029,
    "tags": [
      "amet",
      "Lorem",
      "irure",
      "laboris",
      "deserunt",
      "do",
      "ea"
    ],
    "friends": [
      {
        "id": 0,
        "name": "Shaffer Dawson"
      },
      {
        "id": 1,
        "name": "Lesley Stevens"
      },
      {
        "id": 2,
        "name": "Jaclyn Owens"
      }
    ],
    "greeting": "Hello, Marissa Olson! You have 6 unread messages.",
    "favoriteFruit": "strawberry"
  },
  {
    "_id": "660091d5fcb3b3b9c74e5ff9",
    "index": 6,
    "guid": "0aa076ce-82ac-466e-b906-4da834f6e787",
    "isActive": false,
    "balance": "$3,474.70",
    "picture": "http://placehold.it/32x32",
    "age": 23,
    "eyeColor": "green",
    "name": "Alyce Fisher",
    "gender": "female",
    "company": "ACUMENTOR",
    "email": "alycefisher@acumentor.com",
    "phone": "+1 (874) 577-3498",
    "address": "418 Bills Place, Ronco, New Jersey, 7692",
    "about": "Mollit aute cillum exercitation ex laboris enim labore commodo ex in. Et commodo nostrud duis amet laborum labore aliquip. Nostrud mollit irure culpa velit culpa nostrud. Incididunt sint exercitation mollit aute consequat dolor irure aliqua et sit qui adipisicing tempor esse. Irure laboris laborum incididunt Lorem dolore deserunt id laboris dolor incididunt do est.\r\n",
    "registered": "2017-06-25T05:51:26 +04:00",
    "latitude": -29.999222,
    "longitude": 115.598223,
    "tags": [
      "do",
      "ipsum",
      "consectetur",
      "ipsum",
      "commodo",
      "incididunt",
      "occaecat"
    ],
    "friends": [
      {
        "id": 0,
        "name": "Coffey Brock"
      },
      {
        "id": 1,
        "name": "Harmon Joyner"
      },
      {
        "id": 2,
        "name": "Fuentes Buckner"
      }
    ],
    "greeting": "Hello, Alyce Fisher! You have 2 unread messages.",
    "favoriteFruit": "strawberry"
  }
]
